pycolorprint/__init__.py
pycolorprint/_old_.py
pycolorprint/c_print.py
pycolorprint-1.0.1.dist-info/METADATA
pycolorprint-1.0.1.dist-info/WHEEL
pycolorprint-1.0.1.dist-info/top_level.txt
pycolorprint-1.0.1.dist-info/RECORD
